{
  "project_info": {
    "project_number": "499921176000",
    "project_id": "heart-rate-5a23c",
    "storage_bucket": "heart-rate-5a23c.appspot.com"
  },
  "client": [
    {
      "client_info": {
        "mobilesdk_app_id": "1:499921176000:android:50fb4d7787e73fd2fd7425",
        "android_client_info": {
          "package_name": "com.example.android.heartrate"
        }
      },
      "oauth_client": [
        {
          "client_id": "499921176000-tmdpsn374sp6jkcjb89d1oq07bs2aak5.apps.googleusercontent.com",
          "client_type": 3
        }
      ],
      "api_key": [
        {
          "current_key": "AIzaSyANi6emNKKOmpzbIBgGBQ9K-LnyWVdWOjk"
        }
      ],
      "services": {
        "appinvite_service": {
          "other_platform_oauth_client": [
            {
              "client_id": "499921176000-tmdpsn374sp6jkcjb89d1oq07bs2aak5.apps.googleusercontent.com",
              "client_type": 3
            }
          ]
        }
      }
    }
  ],
  "configuration_version": "1"
}